hkopenai/diagram_as_code_mcp_server/__init__.py
hkopenai/diagram_as_code_mcp_server/__main__.py
hkopenai/diagram_as_code_mcp_server/prompt_get_mermaid_js.py
hkopenai/diagram_as_code_mcp_server/server.py
hkopenai/diagram_as_code_mcp_server/tool_fix_mermaid_js.py
hkopenai_diagram_as_code_mcp_server-0.2.1.dist-info/licenses/LICENSE
hkopenai_diagram_as_code_mcp_server-0.2.1.dist-info/METADATA
hkopenai_diagram_as_code_mcp_server-0.2.1.dist-info/WHEEL
hkopenai_diagram_as_code_mcp_server-0.2.1.dist-info/entry_points.txt
hkopenai_diagram_as_code_mcp_server-0.2.1.dist-info/top_level.txt
hkopenai_diagram_as_code_mcp_server-0.2.1.dist-info/RECORD
