Metadata-Version: 2.4
Name: hkopenai.diagram_as_code_mcp_server
Version: 0.2.1
Summary: This is a MCP server to provide mermaid js validation tools and prompt for MCP client
Author-email: Neo Chow <neo@01man.com>
License-Expression: MIT
Project-URL: repository, https://github.com/hkopenai/hk-prompt-mcp-server.git
Classifier: Programming Language :: Python :: 3
Classifier: Operating System :: OS Independent
Requires-Python: >=3.10
License-File: LICENSE
Requires-Dist: fastmcp>=0.1.0
Requires-Dist: pytest>=8.2.0
Requires-Dist: pytest-cov>=6.1.1
Dynamic: license-file
